{
    "name": "0a241a81-6fa95e97",
    "frames": [
        {
            "timestamp": 10000,
            "objects": [
                {
                    "category": "car",
                    "id": 0,
                    "attributes": {
                        "occluded": true,
                        "truncated": false,
                        "trafficLightColor": "none"
                    },
                    "box2d": {
                        "x1": 617.856601,
                        "y1": 347.962255,
                        "x2": 631.356592,
                        "y2": 361.462245
                    }
                },
                {
                    "category": "car",
                    "id": 1,
                    "attributes": {
                        "occluded": true,
                        "truncated": false,
                        "trafficLightColor": "none"
                    },
                    "box2d": {
                        "x1": 609.419107,
                        "y1": 347.962255,
                        "x2": 624.606597,
                        "y2": 366.524743
                    }
                },
                {
                    "category": "car",
                    "id": 2,
                    "attributes": {
                        "occluded": true,
                        "truncated": false,
                        "trafficLightColor": "none"
                    },
                    "box2d": {
                        "x1": 599.294114,
                        "y1": 351.337253,
                        "x2": 617.856602,
                        "y2": 374.962237
                    }
                },
                {
                    "category": "car",
                    "id": 3,
                    "attributes": {
                        "occluded": true,
                        "truncated": false,
                        "trafficLightColor": "none"
                    },
                    "box2d": {
                        "x1": 827.106458,
                        "y1": 309.149782,
                        "x2": 909.793902,
                        "y2": 400.274719
                    }
                },
                {
                    "category": "car",
                    "id": 4,
                    "attributes": {
                        "occluded": true,
                        "truncated": false,
                        "trafficLightColor": "none"
                    },
                    "box2d": {
                        "x1": 705.606541,
                        "y1": 344.587258,
                        "x2": 720.794031,
                        "y2": 361.462245
                    }
                },
                {
                    "category": "car",
                    "id": 5,
                    "attributes": {
                        "occluded": true,
                        "truncated": false,
                        "trafficLightColor": "none"
                    },
                    "box2d": {
                        "x1": 714.044034,
                        "y1": 344.587258,
                        "x2": 727.544027,
                        "y2": 369.89974
                    }
                },
                {
                    "category": "car",
                    "id": 6,
                    "attributes": {
                        "occluded": false,
                        "truncated": false,
                        "trafficLightColor": "none"
                    },
                    "box2d": {
                        "x1": 577.356629,
                        "y1": 349.649755,
                        "x2": 609.419107,
                        "y2": 376.649738
                    }
                },
                {
                    "category": "car",
                    "id": 7,
                    "attributes": {
                        "occluded": false,
                        "truncated": false,
                        "trafficLightColor": "none"
                    },
                    "box2d": {
                        "x1": 719.106532,
                        "y1": 344.587258,
                        "x2": 761.294003,
                        "y2": 378.337235
                    }
                },
                {
                    "category": "car",
                    "id": 8,
                    "attributes": {
                        "occluded": false,
                        "truncated": false,
                        "trafficLightColor": "none"
                    },
                    "box2d": {
                        "x1": 870.981427,
                        "y1": 290.587295,
                        "x2": 1059.981297,
                        "y2": 415.462209
                    }
                },
                {
                    "category": "car",
                    "id": 9,
                    "attributes": {
                        "occluded": false,
                        "truncated": true,
                        "trafficLightColor": "none"
                    },
                    "box2d": {
                        "x1": 1200.043701,
                        "y1": 331.087267,
                        "x2": 1279.356149,
                        "y2": 449.212186
                    }
                },
                {
                    "category": "area/drivable",
                    "id": 10,
                    "attributes": {},
                    "poly2d": [
                        [
                            617.638251,
                            524.056698,
                            "L"
                        ],
                        [
                            821.02216,
                            495.358355,
                            "C"
                        ],
                        [
                            1026.901577,
                            477.889798,
                            "C"
                        ],
                        [
                            1221.551208,
                            470.403274,
                            "C"
                        ],
                        [
                            1184.118587,
                            431.722899,
                            "L"
                        ],
                        [
                            1066.829707,
                            416.74985,
                            "L"
                        ],
                        [
                            933.320024,
                            427.979637,
                            "L"
                        ],
                        [
                            799.810341,
                            393.042523,
                            "L"
                        ],
                        [
                            799.810341,
                            381.812737,
                            "L"
                        ],
                        [
                            772.359752,
                            376.821721,
                            "L"
                        ],
                        [
                            717.458575,
                            383.060491,
                            "L"
                        ],
                        [
                            707.476542,
                            368.087443,
                            "L"
                        ],
                        [
                            667.548413,
                            371.830705,
                            "L"
                        ],
                        [
                            617.638251,
                            524.056698,
                            "L"
                        ]
                    ]
                },
                {
                    "category": "lane/double yellow",
                    "id": 11,
                    "attributes": {
                        "direction": "parallel",
                        "style": "solid"
                    },
                    "poly2d": [
                        [
                            667.977621,
                            380.814913,
                            "L"
                        ],
                        [
                            615.769125,
                            525.15605,
                            "L"
                        ]
                    ]
                },
                {
                    "category": "lane/double yellow",
                    "id": 12,
                    "attributes": {
                        "direction": "parallel",
                        "style": "solid"
                    },
                    "poly2d": [
                        [
                            649.551093,
                            380.814913,
                            "L"
                        ],
                        [
                            557.418453,
                            531.298226,
                            "L"
                        ]
                    ]
                },
                {
                    "category": "lane/road curb",
                    "id": 13,
                    "attributes": {
                        "direction": "parallel",
                        "style": "solid"
                    },
                    "poly2d": [
                        [
                            525.172029,
                            386.957089,
                            "L"
                        ],
                        [
                            0,
                            480.625274,
                            "L"
                        ]
                    ]
                },
                {
                    "category": "lane/road curb",
                    "id": 14,
                    "attributes": {
                        "direction": "parallel",
                        "style": "solid"
                    },
                    "poly2d": [
                        [
                            1025.759374,
                            414.596881,
                            "L"
                        ],
                        [
                            1210.024655,
                            439.165585,
                            "L"
                        ]
                    ]
                }
            ]
        }
    ],
    "attributes": {
        "weather": "clear",
        "scene": "city street",
        "timeofday": "night"
    }
}