{
    "name": "0b68157c-9780d718",
    "frames": [
        {
            "timestamp": 10000,
            "objects": [
                {
                    "category": "car",
                    "id": 0,
                    "attributes": {
                        "occluded": true,
                        "truncated": false,
                        "trafficLightColor": "none"
                    },
                    "box2d": {
                        "x1": 404.087873,
                        "y1": 347.862276,
                        "x2": 446.178506,
                        "y2": 367.439314
                    }
                },
                {
                    "category": "car",
                    "id": 1,
                    "attributes": {
                        "occluded": true,
                        "truncated": false,
                        "trafficLightColor": "none"
                    },
                    "box2d": {
                        "x1": 280.752533,
                        "y1": 328.285238,
                        "x2": 404.087873,
                        "y2": 387.995204
                    }
                },
                {
                    "category": "car",
                    "id": 2,
                    "attributes": {
                        "occluded": true,
                        "truncated": false,
                        "trafficLightColor": "none"
                    },
                    "box2d": {
                        "x1": 555.730936,
                        "y1": 351.799384,
                        "x2": 589.011901,
                        "y2": 373.334126
                    }
                },
                {
                    "category": "car",
                    "id": 3,
                    "attributes": {
                        "occluded": true,
                        "truncated": false,
                        "trafficLightColor": "none"
                    },
                    "box2d": {
                        "x1": 589.011901,
                        "y1": 351.799384,
                        "x2": 608.588938,
                        "y2": 375.29183
                    }
                },
                {
                    "category": "car",
                    "id": 4,
                    "attributes": {
                        "occluded": true,
                        "truncated": false,
                        "trafficLightColor": "none"
                    },
                    "box2d": {
                        "x1": 504.830637,
                        "y1": 338.095457,
                        "x2": 557.688639,
                        "y2": 391.932314
                    }
                },
                {
                    "category": "car",
                    "id": 5,
                    "attributes": {
                        "occluded": true,
                        "truncated": false,
                        "trafficLightColor": "none"
                    },
                    "box2d": {
                        "x1": 620.452275,
                        "y1": 350.70866,
                        "x2": 633.177352,
                        "y2": 368.327995
                    }
                },
                {
                    "category": "car",
                    "id": 6,
                    "attributes": {
                        "occluded": true,
                        "truncated": false,
                        "trafficLightColor": "none"
                    },
                    "box2d": {
                        "x1": 626.325387,
                        "y1": 352.666364,
                        "x2": 640.029314,
                        "y2": 371.26455
                    }
                },
                {
                    "category": "car",
                    "id": 7,
                    "attributes": {
                        "occluded": true,
                        "truncated": false,
                        "trafficLightColor": "none"
                    },
                    "box2d": {
                        "x1": 636.113905,
                        "y1": 347.772105,
                        "x2": 662.542906,
                        "y2": 376.15881
                    }
                },
                {
                    "category": "car",
                    "id": 8,
                    "attributes": {
                        "occluded": true,
                        "truncated": false,
                        "trafficLightColor": "none"
                    },
                    "box2d": {
                        "x1": 649.817833,
                        "y1": 346.793253,
                        "x2": 680.162242,
                        "y2": 383.989625
                    }
                },
                {
                    "category": "car",
                    "id": 9,
                    "attributes": {
                        "occluded": true,
                        "truncated": false,
                        "trafficLightColor": "none"
                    },
                    "box2d": {
                        "x1": 661.564055,
                        "y1": 350.70866,
                        "x2": 688.971908,
                        "y2": 393.778144
                    }
                },
                {
                    "category": "car",
                    "id": 10,
                    "attributes": {
                        "occluded": false,
                        "truncated": true,
                        "trafficLightColor": "none"
                    },
                    "box2d": {
                        "x1": 0,
                        "y1": 338.264705,
                        "x2": 247.214473,
                        "y2": 432.234487
                    }
                },
                {
                    "category": "car",
                    "id": 11,
                    "attributes": {
                        "occluded": false,
                        "truncated": false,
                        "trafficLightColor": "none"
                    },
                    "box2d": {
                        "x1": 463.486378,
                        "y1": 348.471277,
                        "x2": 528.090604,
                        "y2": 399.371576
                    }
                },
                {
                    "category": "car",
                    "id": 12,
                    "attributes": {
                        "occluded": false,
                        "truncated": false,
                        "trafficLightColor": "none"
                    },
                    "box2d": {
                        "x1": 673.939536,
                        "y1": 347.492426,
                        "x2": 738.543763,
                        "y2": 409.160096
                    }
                },
                {
                    "category": "car",
                    "id": 13,
                    "attributes": {
                        "occluded": true,
                        "truncated": true,
                        "trafficLightColor": "none"
                    },
                    "box2d": {
                        "x1": 1072.842059,
                        "y1": 339.987889,
                        "x2": 1278.400959,
                        "y2": 433.957672
                    }
                },
                {
                    "category": "area/drivable",
                    "id": 14,
                    "attributes": {},
                    "poly2d": [
                        [
                            606.555861,
                            370.577945,
                            "L"
                        ],
                        [
                            531.314205,
                            428.928617,
                            "L"
                        ],
                        [
                            1.551523,
                            433.535249,
                            "L"
                        ],
                        [
                            0,
                            473.459393,
                            "L"
                        ],
                        [
                            179.674627,
                            467.317217,
                            "C"
                        ],
                        [
                            231.883124,
                            494.957009,
                            "C"
                        ],
                        [
                            0,
                            547.165506,
                            "C"
                        ],
                        [
                            0,
                            720.170138,
                            "L"
                        ],
                        [
                            1280.6437,
                            720.170138,
                            "L"
                        ],
                        [
                            1280.6437,
                            611.658354,
                            "L"
                        ],
                        [
                            1168.564967,
                            571.73421,
                            "C"
                        ],
                        [
                            875.276062,
                            481.137113,
                            "C"
                        ],
                        [
                            1041.114814,
                            465.781673,
                            "C"
                        ],
                        [
                            1033.437094,
                            433.535249,
                            "L"
                        ],
                        [
                            929.020102,
                            421.250897,
                            "C"
                        ],
                        [
                            884.489326,
                            433.535249,
                            "C"
                        ],
                        [
                            744.754821,
                            415.108721,
                            "C"
                        ],
                        [
                            664.906533,
                            412.037633,
                            "L"
                        ],
                        [
                            624.982389,
                            373.649033,
                            "L"
                        ],
                        [
                            606.555861,
                            370.577945,
                            "L"
                        ]
                    ]
                },
                {
                    "category": "lane/road curb",
                    "id": 15,
                    "attributes": {
                        "direction": "parallel",
                        "style": "solid"
                    },
                    "poly2d": [
                        [
                            3.743262,
                            550.259533,
                            "C"
                        ],
                        [
                            101.068077,
                            521.56119,
                            "C"
                        ],
                        [
                            170.942304,
                            504.092633,
                            "C"
                        ],
                        [
                            139.748453,
                            481.63306,
                            "L"
                        ]
                    ]
                },
                {
                    "category": "lane/road curb",
                    "id": 16,
                    "attributes": {
                        "direction": "parallel",
                        "style": "solid"
                    },
                    "poly2d": [
                        [
                            1256.488321,
                            600.169695,
                            "L"
                        ],
                        [
                            1088.041525,
                            547.764025,
                            "L"
                        ]
                    ]
                },
                {
                    "category": "lane/road curb",
                    "id": 17,
                    "attributes": {
                        "direction": "parallel",
                        "style": "solid"
                    },
                    "poly2d": [
                        [
                            754.891196,
                            414.254342,
                            "C"
                        ],
                        [
                            772.359752,
                            427.979637,
                            "C"
                        ],
                        [
                            933.320024,
                            426.731883,
                            "C"
                        ],
                        [
                            1041.874626,
                            426.731883,
                            "L"
                        ]
                    ]
                },
                {
                    "category": "lane/crosswalk",
                    "id": 18,
                    "attributes": {
                        "direction": "vertical",
                        "style": "dashed"
                    },
                    "poly2d": [
                        [
                            205.879417,
                            469.15552,
                            "C"
                        ],
                        [
                            255.789579,
                            452.934718,
                            "C"
                        ],
                        [
                            308.195249,
                            437.961669,
                            "C"
                        ],
                        [
                            364.34418,
                            429.227391,
                            "L"
                        ]
                    ]
                },
                {
                    "category": "lane/crosswalk",
                    "id": 19,
                    "attributes": {
                        "direction": "vertical",
                        "style": "dashed"
                    },
                    "poly2d": [
                        [
                            340.636854,
                            426.731883,
                            "C"
                        ],
                        [
                            283.240168,
                            439.209423,
                            "C"
                        ],
                        [
                            220.852466,
                            456.67798,
                            "C"
                        ],
                        [
                            185.915352,
                            469.15552,
                            "L"
                        ]
                    ]
                },
                {
                    "category": "lane/crosswalk",
                    "id": 20,
                    "attributes": {
                        "direction": "vertical",
                        "style": "dashed"
                    },
                    "poly2d": [
                        [
                            9.982032,
                            469.15552,
                            "C"
                        ],
                        [
                            64.88321,
                            452.934718,
                            "C"
                        ],
                        [
                            126.023158,
                            439.209423,
                            "C"
                        ],
                        [
                            195.897385,
                            431.722899,
                            "L"
                        ]
                    ]
                },
                {
                    "category": "lane/crosswalk",
                    "id": 21,
                    "attributes": {
                        "direction": "vertical",
                        "style": "dashed"
                    },
                    "poly2d": [
                        [
                            1.247754,
                            464.164504,
                            "C"
                        ],
                        [
                            73.617489,
                            446.695947,
                            "C"
                        ],
                        [
                            131.014174,
                            434.218407,
                            "C"
                        ],
                        [
                            185.915352,
                            429.227391,
                            "L"
                        ]
                    ]
                },
                {
                    "category": "lane/road curb",
                    "id": 22,
                    "attributes": {
                        "direction": "parallel",
                        "style": "solid"
                    },
                    "poly2d": [
                        [
                            385.555999,
                            424.236375,
                            "C"
                        ],
                        [
                            409.263326,
                            425.484129,
                            "C"
                        ],
                        [
                            425.484129,
                            421.740866,
                            "C"
                        ],
                        [
                            452.934718,
                            406.767818,
                            "L"
                        ]
                    ]
                },
                {
                    "category": "lane/crosswalk",
                    "id": 23,
                    "attributes": {
                        "direction": "vertical",
                        "style": "dashed"
                    },
                    "poly2d": [
                        [
                            974.495907,
                            471.651028,
                            "C"
                        ],
                        [
                            943.302056,
                            456.67798,
                            "C"
                        ],
                        [
                            919.594729,
                            447.943701,
                            "C"
                        ],
                        [
                            884.657616,
                            434.218407,
                            "L"
                        ]
                    ]
                },
                {
                    "category": "lane/crosswalk",
                    "id": 24,
                    "attributes": {
                        "direction": "vertical",
                        "style": "dashed"
                    },
                    "poly2d": [
                        [
                            999.450988,
                            471.651028,
                            "C"
                        ],
                        [
                            955.779597,
                            451.686963,
                            "C"
                        ],
                        [
                            930.824516,
                            441.704931,
                            "C"
                        ],
                        [
                            893.391895,
                            431.722899,
                            "L"
                        ]
                    ]
                },
                {
                    "category": "lane/crosswalk",
                    "id": 25,
                    "attributes": {
                        "direction": "vertical",
                        "style": "dashed"
                    },
                    "poly2d": [
                        [
                            1000.698742,
                            431.722899,
                            "L"
                        ],
                        [
                            1055.59992,
                            435.466161,
                            "L"
                        ]
                    ]
                }
            ]
        }
    ],
    "attributes": {
        "weather": "clear",
        "scene": "residential",
        "timeofday": "daytime"
    }
}