{
    "name": "1a88c5c1-52b956c3",
    "frames": [
        {
            "timestamp": 10000,
            "objects": [
                {
                    "category": "traffic sign",
                    "id": 0,
                    "attributes": {
                        "occluded": false,
                        "truncated": false,
                        "trafficLightColor": "none"
                    },
                    "box2d": {
                        "x1": 883.409861,
                        "y1": 305.69974,
                        "x2": 910.860451,
                        "y2": 331.902576
                    }
                },
                {
                    "category": "car",
                    "id": 1,
                    "attributes": {
                        "occluded": false,
                        "truncated": false,
                        "trafficLightColor": "none"
                    },
                    "box2d": {
                        "x1": 92.333799,
                        "y1": 346.875625,
                        "x2": 500.349371,
                        "y2": 534.03873
                    }
                },
                {
                    "category": "car",
                    "id": 2,
                    "attributes": {
                        "occluded": true,
                        "truncated": false,
                        "trafficLightColor": "none"
                    },
                    "box2d": {
                        "x1": 452.934717,
                        "y1": 349.371132,
                        "x2": 598.92194,
                        "y2": 461.668995
                    }
                },
                {
                    "category": "car",
                    "id": 3,
                    "attributes": {
                        "occluded": false,
                        "truncated": false,
                        "trafficLightColor": "none"
                    },
                    "box2d": {
                        "x1": 641.345578,
                        "y1": 344.380116,
                        "x2": 706.228788,
                        "y2": 395.538032
                    }
                },
                {
                    "category": "car",
                    "id": 4,
                    "attributes": {
                        "occluded": false,
                        "truncated": true,
                        "trafficLightColor": "none"
                    },
                    "box2d": {
                        "x1": 994.459972,
                        "y1": 353.114394,
                        "x2": 1279.356147,
                        "y2": 506.588141
                    }
                },
                {
                    "category": "car",
                    "id": 5,
                    "attributes": {
                        "occluded": true,
                        "truncated": false,
                        "trafficLightColor": "none"
                    },
                    "box2d": {
                        "x1": 697.169047,
                        "y1": 356.857656,
                        "x2": 716.210821,
                        "y2": 383.060492
                    }
                },
                {
                    "category": "car",
                    "id": 6,
                    "attributes": {
                        "occluded": true,
                        "truncated": false,
                        "trafficLightColor": "none"
                    },
                    "box2d": {
                        "x1": 712.356536,
                        "y1": 351.86664,
                        "x2": 727.440606,
                        "y2": 379.31723
                    }
                },
                {
                    "category": "car",
                    "id": 7,
                    "attributes": {
                        "occluded": true,
                        "truncated": false,
                        "trafficLightColor": "none"
                    },
                    "box2d": {
                        "x1": 722.44959,
                        "y1": 351.86664,
                        "x2": 736.174884,
                        "y2": 373.078459
                    }
                },
                {
                    "category": "car",
                    "id": 8,
                    "attributes": {
                        "occluded": true,
                        "truncated": false,
                        "trafficLightColor": "none"
                    },
                    "box2d": {
                        "x1": 731.183868,
                        "y1": 351.86664,
                        "x2": 752.395686,
                        "y2": 368.087443
                    }
                },
                {
                    "category": "car",
                    "id": 9,
                    "attributes": {
                        "occluded": false,
                        "truncated": false,
                        "trafficLightColor": "none"
                    },
                    "box2d": {
                        "x1": 753.643442,
                        "y1": 356.857656,
                        "x2": 764.873228,
                        "y2": 369.335196
                    }
                },
                {
                    "category": "car",
                    "id": 10,
                    "attributes": {
                        "occluded": true,
                        "truncated": false,
                        "trafficLightColor": "none"
                    },
                    "box2d": {
                        "x1": 893.391895,
                        "y1": 333.150329,
                        "x2": 1036.88361,
                        "y2": 432.970653
                    }
                },
                {
                    "category": "car",
                    "id": 11,
                    "attributes": {
                        "occluded": true,
                        "truncated": false,
                        "trafficLightColor": "none"
                    },
                    "box2d": {
                        "x1": 855.959272,
                        "y1": 340.636854,
                        "x2": 914.603713,
                        "y2": 405.520064
                    }
                },
                {
                    "category": "car",
                    "id": 12,
                    "attributes": {
                        "occluded": true,
                        "truncated": false,
                        "trafficLightColor": "none"
                    },
                    "box2d": {
                        "x1": 838.490716,
                        "y1": 351.86664,
                        "x2": 865.941305,
                        "y2": 394.290278
                    }
                },
                {
                    "category": "car",
                    "id": 13,
                    "attributes": {
                        "occluded": true,
                        "truncated": false,
                        "trafficLightColor": "none"
                    },
                    "box2d": {
                        "x1": 827.26093,
                        "y1": 359.353165,
                        "x2": 843.481732,
                        "y2": 384.308245
                    }
                },
                {
                    "category": "car",
                    "id": 14,
                    "attributes": {
                        "occluded": true,
                        "truncated": false,
                        "trafficLightColor": "none"
                    },
                    "box2d": {
                        "x1": 817.278898,
                        "y1": 351.86664,
                        "x2": 847.224994,
                        "y2": 376.821721
                    }
                },
                {
                    "category": "car",
                    "id": 15,
                    "attributes": {
                        "occluded": true,
                        "truncated": false,
                        "trafficLightColor": "none"
                    },
                    "box2d": {
                        "x1": 811.040129,
                        "y1": 363.096425,
                        "x2": 822.269915,
                        "y2": 378.069474
                    }
                },
                {
                    "category": "car",
                    "id": 16,
                    "attributes": {
                        "occluded": true,
                        "truncated": false,
                        "trafficLightColor": "none"
                    },
                    "box2d": {
                        "x1": 802.305849,
                        "y1": 354.362147,
                        "x2": 822.269914,
                        "y2": 373.078459
                    }
                },
                {
                    "category": "car",
                    "id": 17,
                    "attributes": {
                        "occluded": true,
                        "truncated": false,
                        "trafficLightColor": "none"
                    },
                    "box2d": {
                        "x1": 794.819325,
                        "y1": 356.857656,
                        "x2": 809.792374,
                        "y2": 368.087443
                    }
                },
                {
                    "category": "car",
                    "id": 18,
                    "attributes": {
                        "occluded": true,
                        "truncated": false,
                        "trafficLightColor": "none"
                    },
                    "box2d": {
                        "x1": 787.332802,
                        "y1": 354.362147,
                        "x2": 797.314833,
                        "y2": 365.591934
                    }
                },
                {
                    "category": "area/drivable",
                    "id": 19,
                    "attributes": {},
                    "poly2d": [
                        [
                            769.323525,
                            368.530561,
                            "L"
                        ],
                        [
                            790.821141,
                            370.066105,
                            "L"
                        ],
                        [
                            1067.219062,
                            515.942785,
                            "L"
                        ],
                        [
                            1280.6437,
                            512.871698,
                            "L"
                        ],
                        [
                            1280.6437,
                            657.212834,
                            "L"
                        ],
                        [
                            1128.640822,
                            651.070658,
                            "L"
                        ],
                        [
                            976.621965,
                            624.96641,
                            "C"
                        ],
                        [
                            836.887463,
                            603.468794,
                            "C"
                        ],
                        [
                            661.835445,
                            588.113353,
                            "C"
                        ],
                        [
                            769.323525,
                            368.530561,
                            "L"
                        ]
                    ]
                },
                {
                    "category": "lane/road curb",
                    "id": 20,
                    "attributes": {
                        "direction": "parallel",
                        "style": "solid"
                    },
                    "poly2d": [
                        [
                            129.343906,
                            535.304483,
                            "L"
                        ],
                        [
                            0,
                            569.686826,
                            "L"
                        ]
                    ]
                }
            ]
        }
    ],
    "attributes": {
        "weather": "partly cloudy",
        "scene": "residential",
        "timeofday": "daytime"
    }
}