<?xml version="1.0" ?>
<annotation>
    <folder>./bdd100/labels-mini-xml</folder>
    <filename>01e5bbac-330a3c37</filename>
    <path/>
    <source>
        <database>./bdd100/labels-mini/01e5bbac-330a3c37.json</database>
    </source>
    <size>
        <width>1280</width>
        <height>720</height>
        <depth>3</depth>
    </size>
    <segmented>0</segmented>
    <object>
        <name>car</name>
        <pose>Unspecified</pose>
        <truncated>0</truncated>
        <Difficult>0</Difficult>
        <bndbox>
            <xmin>727</xmin>
            <ymin>484</ymin>
            <xmax>756</xmax>
            <ymax>516</ymax>
        </bndbox>
    </object>
    <object>
        <name>car</name>
        <pose>Unspecified</pose>
        <truncated>0</truncated>
        <Difficult>0</Difficult>
        <bndbox>
            <xmin>671</xmin>
            <ymin>486</ymin>
            <xmax>736</xmax>
            <ymax>524</ymax>
        </bndbox>
    </object>
    <object>
        <name>car</name>
        <pose>Unspecified</pose>
        <truncated>0</truncated>
        <Difficult>0</Difficult>
        <bndbox>
            <xmin>758</xmin>
            <ymin>491</ymin>
            <xmax>778</xmax>
            <ymax>523</ymax>
        </bndbox>
    </object>
    <object>
        <name>car</name>
        <pose>Unspecified</pose>
        <truncated>0</truncated>
        <Difficult>0</Difficult>
        <bndbox>
            <xmin>768</xmin>
            <ymin>489</ymin>
            <xmax>818</xmax>
            <ymax>546</ymax>
        </bndbox>
    </object>
    <object>
        <name>car</name>
        <pose>Unspecified</pose>
        <truncated>0</truncated>
        <Difficult>0</Difficult>
        <bndbox>
            <xmin>794</xmin>
            <ymin>486</ymin>
            <xmax>889</xmax>
            <ymax>572</ymax>
        </bndbox>
    </object>
    <object>
        <name>car</name>
        <pose>Unspecified</pose>
        <truncated>0</truncated>
        <Difficult>0</Difficult>
        <bndbox>
            <xmin>1078</xmin>
            <ymin>481</ymin>
            <xmax>1156</xmax>
            <ymax>535</ymax>
        </bndbox>
    </object>
    <object>
        <name>truck</name>
        <pose>Unspecified</pose>
        <truncated>0</truncated>
        <Difficult>0</Difficult>
        <bndbox>
            <xmin>831</xmin>
            <ymin>409</ymin>
            <xmax>978</xmax>
            <ymax>493</ymax>
        </bndbox>
    </object>
    <object>
        <name>car</name>
        <pose>Unspecified</pose>
        <truncated>0</truncated>
        <Difficult>0</Difficult>
        <bndbox>
            <xmin>560</xmin>
            <ymin>461</ymin>
            <xmax>741</xmax>
            <ymax>635</ymax>
        </bndbox>
    </object>
    <object>
        <name>car</name>
        <pose>Unspecified</pose>
        <truncated>0</truncated>
        <Difficult>0</Difficult>
        <bndbox>
            <xmin>848</xmin>
            <ymin>469</ymin>
            <xmax>1135</xmax>
            <ymax>647</ymax>
        </bndbox>
    </object>
    <object>
        <name>truck</name>
        <pose>Unspecified</pose>
        <truncated>0</truncated>
        <Difficult>0</Difficult>
        <bndbox>
            <xmin>1110</xmin>
            <ymin>465</ymin>
            <xmax>1277</xmax>
            <ymax>619</ymax>
        </bndbox>
    </object>
    <object>
        <name>traffic light</name>
        <pose>Unspecified</pose>
        <truncated>0</truncated>
        <Difficult>0</Difficult>
        <bndbox>
            <xmin>779</xmin>
            <ymin>412</ymin>
            <xmax>791</xmax>
            <ymax>441</ymax>
        </bndbox>
    </object>
</annotation>
