<?xml version="1.0" ?>
<annotation>
    <folder>./bdd100/labels-mini-xml</folder>
    <filename>0d202fb6-32385e70</filename>
    <path/>
    <source>
        <database>./bdd100/labels-mini/0d202fb6-32385e70.json</database>
    </source>
    <size>
        <width>1280</width>
        <height>720</height>
        <depth>3</depth>
    </size>
    <segmented>0</segmented>
    <object>
        <name>car</name>
        <pose>Unspecified</pose>
        <truncated>0</truncated>
        <Difficult>0</Difficult>
        <bndbox>
            <xmin>0</xmin>
            <ymin>245</ymin>
            <xmax>323</xmax>
            <ymax>502</ymax>
        </bndbox>
    </object>
    <object>
        <name>car</name>
        <pose>Unspecified</pose>
        <truncated>0</truncated>
        <Difficult>0</Difficult>
        <bndbox>
            <xmin>475</xmin>
            <ymin>232</ymin>
            <xmax>749</xmax>
            <ymax>546</ymax>
        </bndbox>
    </object>
    <object>
        <name>bus</name>
        <pose>Unspecified</pose>
        <truncated>0</truncated>
        <Difficult>0</Difficult>
        <bndbox>
            <xmin>758</xmin>
            <ymin>182</ymin>
            <xmax>1095</xmax>
            <ymax>482</ymax>
        </bndbox>
    </object>
    <object>
        <name>bus</name>
        <pose>Unspecified</pose>
        <truncated>0</truncated>
        <Difficult>0</Difficult>
        <bndbox>
            <xmin>631</xmin>
            <ymin>244</ymin>
            <xmax>766</xmax>
            <ymax>393</ymax>
        </bndbox>
    </object>
    <object>
        <name>car</name>
        <pose>Unspecified</pose>
        <truncated>0</truncated>
        <Difficult>0</Difficult>
        <bndbox>
            <xmin>257</xmin>
            <ymin>291</ymin>
            <xmax>425</xmax>
            <ymax>432</ymax>
        </bndbox>
    </object>
    <object>
        <name>car</name>
        <pose>Unspecified</pose>
        <truncated>0</truncated>
        <Difficult>0</Difficult>
        <bndbox>
            <xmin>408</xmin>
            <ymin>311</ymin>
            <xmax>501</xmax>
            <ymax>398</ymax>
        </bndbox>
    </object>
    <object>
        <name>car</name>
        <pose>Unspecified</pose>
        <truncated>0</truncated>
        <Difficult>0</Difficult>
        <bndbox>
            <xmin>452</xmin>
            <ymin>298</ymin>
            <xmax>516</xmax>
            <ymax>326</ymax>
        </bndbox>
    </object>
    <object>
        <name>motor</name>
        <pose>Unspecified</pose>
        <truncated>0</truncated>
        <Difficult>0</Difficult>
        <bndbox>
            <xmin>1207</xmin>
            <ymin>383</ymin>
            <xmax>1275</xmax>
            <ymax>534</ymax>
        </bndbox>
    </object>
    <object>
        <name>person</name>
        <pose>Unspecified</pose>
        <truncated>0</truncated>
        <Difficult>0</Difficult>
        <bndbox>
            <xmin>1100</xmin>
            <ymin>296</ymin>
            <xmax>1144</xmax>
            <ymax>398</ymax>
        </bndbox>
    </object>
    <object>
        <name>person</name>
        <pose>Unspecified</pose>
        <truncated>0</truncated>
        <Difficult>0</Difficult>
        <bndbox>
            <xmin>1136</xmin>
            <ymin>311</ymin>
            <xmax>1175</xmax>
            <ymax>406</ymax>
        </bndbox>
    </object>
    <object>
        <name>traffic sign</name>
        <pose>Unspecified</pose>
        <truncated>0</truncated>
        <Difficult>0</Difficult>
        <bndbox>
            <xmin>252</xmin>
            <ymin>260</ymin>
            <xmax>296</xmax>
            <ymax>281</ymax>
        </bndbox>
    </object>
</annotation>
