<?xml version="1.0" ?>
<annotation>
    <folder>./bdd100/labels-mini-xml</folder>
    <filename>0d6b7f11-1bf62abe</filename>
    <path/>
    <source>
        <database>./bdd100/labels-mini/0d6b7f11-1bf62abe.json</database>
    </source>
    <size>
        <width>1280</width>
        <height>720</height>
        <depth>3</depth>
    </size>
    <segmented>0</segmented>
    <object>
        <name>car</name>
        <pose>Unspecified</pose>
        <truncated>0</truncated>
        <Difficult>0</Difficult>
        <bndbox>
            <xmin>510</xmin>
            <ymin>386</ymin>
            <xmax>531</xmax>
            <ymax>405</ymax>
        </bndbox>
    </object>
    <object>
        <name>car</name>
        <pose>Unspecified</pose>
        <truncated>0</truncated>
        <Difficult>0</Difficult>
        <bndbox>
            <xmin>510</xmin>
            <ymin>390</ymin>
            <xmax>523</xmax>
            <ymax>407</ymax>
        </bndbox>
    </object>
    <object>
        <name>car</name>
        <pose>Unspecified</pose>
        <truncated>0</truncated>
        <Difficult>0</Difficult>
        <bndbox>
            <xmin>501</xmin>
            <ymin>391</ymin>
            <xmax>522</xmax>
            <ymax>410</ymax>
        </bndbox>
    </object>
    <object>
        <name>car</name>
        <pose>Unspecified</pose>
        <truncated>0</truncated>
        <Difficult>0</Difficult>
        <bndbox>
            <xmin>451</xmin>
            <ymin>397</ymin>
            <xmax>486</xmax>
            <ymax>428</ymax>
        </bndbox>
    </object>
    <object>
        <name>car</name>
        <pose>Unspecified</pose>
        <truncated>0</truncated>
        <Difficult>0</Difficult>
        <bndbox>
            <xmin>415</xmin>
            <ymin>396</ymin>
            <xmax>468</xmax>
            <ymax>435</ymax>
        </bndbox>
    </object>
    <object>
        <name>car</name>
        <pose>Unspecified</pose>
        <truncated>0</truncated>
        <Difficult>0</Difficult>
        <bndbox>
            <xmin>416</xmin>
            <ymin>403</ymin>
            <xmax>455</xmax>
            <ymax>440</ymax>
        </bndbox>
    </object>
    <object>
        <name>car</name>
        <pose>Unspecified</pose>
        <truncated>0</truncated>
        <Difficult>0</Difficult>
        <bndbox>
            <xmin>364</xmin>
            <ymin>400</ymin>
            <xmax>436</xmax>
            <ymax>456</ymax>
        </bndbox>
    </object>
    <object>
        <name>car</name>
        <pose>Unspecified</pose>
        <truncated>0</truncated>
        <Difficult>0</Difficult>
        <bndbox>
            <xmin>288</xmin>
            <ymin>396</ymin>
            <xmax>373</xmax>
            <ymax>472</ymax>
        </bndbox>
    </object>
    <object>
        <name>car</name>
        <pose>Unspecified</pose>
        <truncated>0</truncated>
        <Difficult>0</Difficult>
        <bndbox>
            <xmin>559</xmin>
            <ymin>368</ymin>
            <xmax>628</xmax>
            <ymax>430</ymax>
        </bndbox>
    </object>
    <object>
        <name>car</name>
        <pose>Unspecified</pose>
        <truncated>0</truncated>
        <Difficult>0</Difficult>
        <bndbox>
            <xmin>526</xmin>
            <ymin>395</ymin>
            <xmax>538</xmax>
            <ymax>403</ymax>
        </bndbox>
    </object>
    <object>
        <name>car</name>
        <pose>Unspecified</pose>
        <truncated>0</truncated>
        <Difficult>0</Difficult>
        <bndbox>
            <xmin>1</xmin>
            <ymin>370</ymin>
            <xmax>357</xmax>
            <ymax>612</ymax>
        </bndbox>
    </object>
    <object>
        <name>traffic sign</name>
        <pose>Unspecified</pose>
        <truncated>0</truncated>
        <Difficult>0</Difficult>
        <bndbox>
            <xmin>13</xmin>
            <ymin>237</ymin>
            <xmax>58</xmax>
            <ymax>258</ymax>
        </bndbox>
    </object>
    <object>
        <name>traffic sign</name>
        <pose>Unspecified</pose>
        <truncated>0</truncated>
        <Difficult>0</Difficult>
        <bndbox>
            <xmin>71</xmin>
            <ymin>255</ymin>
            <xmax>95</xmax>
            <ymax>279</ymax>
        </bndbox>
    </object>
    <object>
        <name>car</name>
        <pose>Unspecified</pose>
        <truncated>0</truncated>
        <Difficult>0</Difficult>
        <bndbox>
            <xmin>553</xmin>
            <ymin>373</ymin>
            <xmax>690</xmax>
            <ymax>502</ymax>
        </bndbox>
    </object>
    <object>
        <name>car</name>
        <pose>Unspecified</pose>
        <truncated>0</truncated>
        <Difficult>0</Difficult>
        <bndbox>
            <xmin>1175</xmin>
            <ymin>371</ymin>
            <xmax>1278</xmax>
            <ymax>493</ymax>
        </bndbox>
    </object>
</annotation>
