<?xml version="1.0" ?>
<annotation>
    <folder>./bdd100/labels-mini-xml</folder>
    <filename>1c89dc5d-12822c89</filename>
    <path/>
    <source>
        <database>./bdd100/labels-mini/1c89dc5d-12822c89.json</database>
    </source>
    <size>
        <width>1280</width>
        <height>720</height>
        <depth>3</depth>
    </size>
    <segmented>0</segmented>
    <object>
        <name>car</name>
        <pose>Unspecified</pose>
        <truncated>0</truncated>
        <Difficult>0</Difficult>
        <bndbox>
            <xmin>1</xmin>
            <ymin>361</ymin>
            <xmax>103</xmax>
            <ymax>513</ymax>
        </bndbox>
    </object>
    <object>
        <name>car</name>
        <pose>Unspecified</pose>
        <truncated>0</truncated>
        <Difficult>0</Difficult>
        <bndbox>
            <xmin>601</xmin>
            <ymin>344</ymin>
            <xmax>732</xmax>
            <ymax>434</ymax>
        </bndbox>
    </object>
    <object>
        <name>car</name>
        <pose>Unspecified</pose>
        <truncated>0</truncated>
        <Difficult>0</Difficult>
        <bndbox>
            <xmin>445</xmin>
            <ymin>355</ymin>
            <xmax>589</xmax>
            <ymax>406</ymax>
        </bndbox>
    </object>
    <object>
        <name>car</name>
        <pose>Unspecified</pose>
        <truncated>0</truncated>
        <Difficult>0</Difficult>
        <bndbox>
            <xmin>845</xmin>
            <ymin>301</ymin>
            <xmax>1214</xmax>
            <ymax>529</ymax>
        </bndbox>
    </object>
    <object>
        <name>car</name>
        <pose>Unspecified</pose>
        <truncated>0</truncated>
        <Difficult>0</Difficult>
        <bndbox>
            <xmin>77</xmin>
            <ymin>347</ymin>
            <xmax>274</xmax>
            <ymax>474</ymax>
        </bndbox>
    </object>
    <object>
        <name>car</name>
        <pose>Unspecified</pose>
        <truncated>0</truncated>
        <Difficult>0</Difficult>
        <bndbox>
            <xmin>762</xmin>
            <ymin>330</ymin>
            <xmax>913</xmax>
            <ymax>464</ymax>
        </bndbox>
    </object>
    <object>
        <name>traffic sign</name>
        <pose>Unspecified</pose>
        <truncated>0</truncated>
        <Difficult>0</Difficult>
        <bndbox>
            <xmin>637</xmin>
            <ymin>315</ymin>
            <xmax>665</xmax>
            <ymax>329</ymax>
        </bndbox>
    </object>
    <object>
        <name>traffic sign</name>
        <pose>Unspecified</pose>
        <truncated>0</truncated>
        <Difficult>0</Difficult>
        <bndbox>
            <xmin>863</xmin>
            <ymin>236</ymin>
            <xmax>907</xmax>
            <ymax>274</ymax>
        </bndbox>
    </object>
    <object>
        <name>traffic sign</name>
        <pose>Unspecified</pose>
        <truncated>0</truncated>
        <Difficult>0</Difficult>
        <bndbox>
            <xmin>873</xmin>
            <ymin>277</ymin>
            <xmax>900</xmax>
            <ymax>301</ymax>
        </bndbox>
    </object>
</annotation>
